{
  "DLSVersion": "2.1.6.10",
  "Name": "4PIN OR",
  "Size": {
    "x": 1.025,
    "y": 1.0
  },
  "Colour": {
    "r": 0.199429333,
    "g": 0.310005337,
    "b": 0.294908881,
    "a": 1
  },
  "InputPins":[
    {
      "Name":"IN",
      "ID":2038808185,
      "Position":{
        "x":5.875,
        "y":6.1875
      },
      "BitCount":"1",
      "face":1
    },
    {
      "Name":"IN",
      "ID":1324858247,
      "Position":{
        "x":5.875,
        "y":5.75
      },
      "BitCount":"1",
      "face":1
    },
    {
      "Name":"IN",
      "ID":1088974645,
      "Position":{
        "x":5.875,
        "y":5.3125
      },
      "BitCount":"1",
      "face":1
    },
    {
      "Name":"IN",
      "ID":1423892814,
      "Position":{
        "x":5.875,
        "y":4.875
      },
      "BitCount":"1",
      "face":1
    }
  ],
  "OutputPins":[
    {
      "Name":"OUT",
      "ID":1524514671,
      "Position":{
        "x":11.875,
        "y":5.375
      },
      "BitCount":"1",
      "face":1
    }
  ],
  "SubChips":[
    {
      "Name":"OR",
      "ID":2016843759,
      "Label":"",
      "Position":{
        "x":9.5975,
        "y":5.625
      },
      "OutputPinColourInfo":[{"PinID":2139116146}]
    },
    {
      "Name":"OR",
      "ID":1744587573,
      "Label":"",
      "Position":{
        "x":9.5975,
        "y":5.0625
      },
      "OutputPinColourInfo":[{"PinID":2139116146}]
    },
    {
      "Name":"OR",
      "ID":176126236,
      "Label":"",
      "Position":{
        "x":10.3475,
        "y":5.375
      },
      "OutputPinColourInfo":[{"PinID":2139116146}]
    }
  ],
  "Wires":[
    {
      "SourcePinAddress":{
        "PinID":2139116146,
        "PinOwnerID":2016843759
      },
      "TargetPinAddress":{
        "PinID":1319087483,
        "PinOwnerID":176126236
      },
      "ConnectedWireIndex":-1,
      "ConnectedWireSegmentIndex":-1,
      "Points":[{"x":0.0,"y":0.0},{"x":0.0,"y":0.0}]
    },
    {
      "SourcePinAddress":{
        "PinID":2139116146,
        "PinOwnerID":1744587573
      },
      "TargetPinAddress":{
        "PinID":689640271,
        "PinOwnerID":176126236
      },
      "ConnectedWireIndex":-1,
      "ConnectedWireSegmentIndex":-1,
      "Points":[{"x":0.0,"y":0.0},{"x":0.0,"y":0.0}]
    },
    {
      "SourcePinAddress":{
        "PinOwnerID":2038808185
      },
      "TargetPinAddress":{
        "PinID":1319087483,
        "PinOwnerID":2016843759
      },
      "ConnectedWireIndex":-1,
      "ConnectedWireSegmentIndex":-1,
      "Points":[{"x":0.0,"y":0.0},{"x":0.0,"y":0.0}]
    },
    {
      "SourcePinAddress":{
        "PinOwnerID":1324858247
      },
      "TargetPinAddress":{
        "PinID":689640271,
        "PinOwnerID":2016843759
      },
      "ConnectedWireIndex":-1,
      "ConnectedWireSegmentIndex":-1,
      "Points":[{"x":0.0,"y":0.0},{"x":0.0,"y":0.0}]
    },
    {
      "SourcePinAddress":{
        "PinOwnerID":1088974645
      },
      "TargetPinAddress":{
        "PinID":1319087483,
        "PinOwnerID":1744587573
      },
      "ConnectedWireIndex":-1,
      "ConnectedWireSegmentIndex":-1,
      "Points":[{"x":0.0,"y":0.0},{"x":0.0,"y":0.0}]
    },
    {
      "SourcePinAddress":{
        "PinOwnerID":1423892814
      },
      "TargetPinAddress":{
        "PinID":689640271,
        "PinOwnerID":1744587573
      },
      "ConnectedWireIndex":-1,
      "ConnectedWireSegmentIndex":-1,
      "Points":[{"x":0.0,"y":0.0},{"x":0.0,"y":0.0}]
    },
    {
      "SourcePinAddress":{
        "PinID":2139116146,
        "PinOwnerID":176126236
      },
      "TargetPinAddress":{
        "PinOwnerID":1524514671
      },
      "ConnectedWireIndex":-1,
      "ConnectedWireSegmentIndex":-1,
      "Points":[{"x":0.0,"y":0.0},{"x":0.0,"y":0.0}]
    }
  ]
}